pyr/.__init__.py.swp
pyr/.optics.py.swp
pyr/.sigexcept.py.swp
pyr/__init__.py
pyr/__main__.py
pyr/console.py
pyr/doctest.py
pyr/examples.py
pyr/optics.py
pyr/sigexcept.py
nfte_pyr-0.6.0.dist-info/licenses/license.md
nfte_pyr-0.6.0.dist-info/WHEEL
nfte_pyr-0.6.0.dist-info/METADATA
nfte_pyr-0.6.0.dist-info/RECORD
