Metadata-Version: 2.4
Name: nfte-pyr
Version: 0.6.0
Summary: Argument parser and general Python front-end
License-File: license.md
Requires-Python: >=3.12
